odoo10_addon_hr_expense_analytic_distribution-10.0.1.0.0-py2.7-nspkg.pth
odoo/addons/hr_expense_analytic_distribution/README.rst
odoo/addons/hr_expense_analytic_distribution/__init__.py
odoo/addons/hr_expense_analytic_distribution/__manifest__.py
odoo/addons/hr_expense_analytic_distribution/i18n/de.po
odoo/addons/hr_expense_analytic_distribution/i18n/es.po
odoo/addons/hr_expense_analytic_distribution/i18n/fi.po
odoo/addons/hr_expense_analytic_distribution/i18n/fr.po
odoo/addons/hr_expense_analytic_distribution/i18n/hr_expense_analytic_plans.pot
odoo/addons/hr_expense_analytic_distribution/i18n/nl.po
odoo/addons/hr_expense_analytic_distribution/i18n/pt_BR.po
odoo/addons/hr_expense_analytic_distribution/i18n/sl.po
odoo/addons/hr_expense_analytic_distribution/models/__init__.py
odoo/addons/hr_expense_analytic_distribution/models/hr_expense.py
odoo/addons/hr_expense_analytic_distribution/static/description/icon.png
odoo/addons/hr_expense_analytic_distribution/tests/__init__.py
odoo/addons/hr_expense_analytic_distribution/tests/test_hr_expense_analytic_distribution.py
odoo/addons/hr_expense_analytic_distribution/views/hr_expense.xml
odoo10_addon_hr_expense_analytic_distribution-10.0.1.0.0.dist-info/DESCRIPTION.rst
odoo10_addon_hr_expense_analytic_distribution-10.0.1.0.0.dist-info/METADATA
odoo10_addon_hr_expense_analytic_distribution-10.0.1.0.0.dist-info/RECORD
odoo10_addon_hr_expense_analytic_distribution-10.0.1.0.0.dist-info/WHEEL
odoo10_addon_hr_expense_analytic_distribution-10.0.1.0.0.dist-info/metadata.json
odoo10_addon_hr_expense_analytic_distribution-10.0.1.0.0.dist-info/namespace_packages.txt
odoo10_addon_hr_expense_analytic_distribution-10.0.1.0.0.dist-info/top_level.txt
